MANIFEST.in
nameko_redis.py
setup.py
nameko_redis.egg-info/PKG-INFO
nameko_redis.egg-info/SOURCES.txt
nameko_redis.egg-info/dependency_links.txt
nameko_redis.egg-info/requires.txt
nameko_redis.egg-info/top_level.txt