Metadata-Version: 1.1
Name: nameko-redis
Version: 1.0.0
Summary: Redis dependency for nameko services
Home-page: https://github.com/etataurov/nameko-redis/
Author: etataurov
Author-email: tatauroff@gmail.com
License: Apache License, Version 2.0
Platform: UNKNOWN
Classifier: Development Status :: 3 - Alpha
Classifier: License :: OSI Approved :: Apache Software License
Classifier: Programming Language :: Python :: 2
Classifier: Programming Language :: Python :: 2.7
Classifier: Programming Language :: Python :: 3
Classifier: Programming Language :: Python :: 3.3
Classifier: Programming Language :: Python :: 3.4
Classifier: Programming Language :: Python :: 3.5
